pycoQC/Fast5_to_seq_summary.py
pycoQC/__init__.py
pycoQC/__main__.py
pycoQC/common.py
pycoQC/pycoQC.py
pycoQC/pycoQC_parse.py
pycoQC/pycoQC_plot.py
pycoQC/pycoQC_report.py
pycoQC/templates/pycoQC_config.json
pycoQC/templates/spectre.html.j2
pycoQC-2.3.0.5.dist-info/METADATA
pycoQC-2.3.0.5.dist-info/RECORD
pycoQC-2.3.0.5.dist-info/WHEEL
pycoQC-2.3.0.5.dist-info/entry_points.txt
pycoQC-2.3.0.5.dist-info/top_level.txt
