Metadata-Version: 2.1
Name: pycoQC
Version: 2.3.0.5
Summary: PycoQC computes metrics and generates interactive QC plots for Oxford Nanopore technologies sequencing data
Home-page: https://github.com/a-slide/pycoQC
Author: Adrien Leger & Tommaso Leonardi
Author-email: aleg@ebi.ac.uk
Maintainer: Adrien Leger
Maintainer-email: aleg@ebi.ac.uk
License: GPLv3
Platform: UNKNOWN
Classifier: Development Status :: 3 - Alpha
Classifier: Intended Audience :: Science/Research
Classifier: Topic :: Scientific/Engineering :: Bio-Informatics
Classifier: License :: OSI Approved :: GNU General Public License v3 (GPLv3)
Classifier: Programming Language :: Python :: 3
Requires-Python: >=3.5
Requires-Dist: numpy (==1.16.4)
Requires-Dist: scipy (==1.2.0)
Requires-Dist: pandas (==0.24.2)
Requires-Dist: plotly (==3.10.0)
Requires-Dist: jinja2 (==2.10.1)
Requires-Dist: h5py (==2.9.0)
Requires-Dist: tqdm (==4.32.1)
